db2_hj3415/__init__.py
db2_hj3415/mongo.py
db2_hj3415/settings.py
db2_hj3415/analysis/__init__.py
db2_hj3415/analysis/domain.py
db2_hj3415/analysis/repo.py
db2_hj3415/common/__init__.py
db2_hj3415/common/hash_utils.py
db2_hj3415/nfs/__init__.py
db2_hj3415/nfs/domain.py
db2_hj3415/nfs/repo.py
db2_hj3415/universe/__init__.py
db2_hj3415/universe/domain.py
db2_hj3415/universe/repo.py
db2_hj3415-2.2.0.dist-info/licenses/LICENSE
db2_hj3415-2.2.0.dist-info/WHEEL
db2_hj3415-2.2.0.dist-info/METADATA
db2_hj3415-2.2.0.dist-info/RECORD
