Metadata-Version: 2.4
Name: db2-hj3415
Version: 2.2.0
Summary: MongoDB storage helpers for NFS (latest/snapshots)
Keywords: example,demo
Author-email: Hyungjin Kim <hj3415@gmail.com>
Requires-Python: >=3.11
Classifier: Programming Language :: Python :: 3
Classifier: License :: OSI Approved :: MIT License
Classifier: Typing :: Typed
License-File: LICENSE
Requires-Dist: pymongo>=4.8
Requires-Dist: pydantic>=2.7
Requires-Dist: pydantic-settings>=2.3
Requires-Dist: contracts-hj3415
Requires-Dist: common-hj3415
